{
  "aor": 0.002808177339901478,
  "aqi": 0.004731211822660099,
  "bids_meta": {
    "EchoTime": 0.03,
    "RepetitionTime": 3.0,
    "SliceEncodingDirection": "k",
    "SliceTiming": [
      0.0,
      1.5,
      0.065,
      1.565,
      0.13,
      1.63,
      0.196,
      1.696,
      0.261,
      1.761,
      0.326,
      1.826,
      0.391,
      1.891,
      0.457,
      1.957,
      0.522,
      2.022,
      0.587,
      2.087,
      0.652,
      2.152,
      0.717,
      2.217,
      0.783,
      2.283,
      0.848,
      2.348,
      0.913,
      2.413,
      0.978,
      2.478,
      1.043,
      2.543,
      1.109,
      2.609,
      1.174,
      2.674,
      1.239,
      2.739,
      1.304,
      2.804,
      1.37,
      2.87,
      1.435,
      2.935
    ],
    "TaskName": "rest",
    "dataset": "ds003592",
    "modality": "bold",
    "session_id": "1",
    "subject_id": "23",
    "task_id": "rest"
  },
  "dummy_trs": 1,
  "dvars_nstd": 20.629562160643566,
  "dvars_std": 1.033658536336634,
  "dvars_vstd": 0.9475631321782185,
  "efc": 0.4857791058177077,
  "fber": 8691.337890625,
  "fd_mean": 0.07467879797225611,
  "fd_num": 4,
  "fd_perc": 1.9704433497536946,
  "fwhm_avg": 2.7646677777777775,
  "fwhm_x": 2.69734,
  "fwhm_y": 2.9131466666666666,
  "fwhm_z": 2.6835166666666663,
  "gcor": 0.0343372,
  "gsr_x": -0.008056399412453175,
  "gsr_y": 0.05034943297505379,
  "provenance": {
    "md5sum": "2a30accd68e88230ede41519c7706534",
    "settings": {
      "fd_thres": 0.2,
      "testing": false
    },
    "software": "mriqc",
    "version": "23.1.0"
  },
  "size_t": 203,
  "size_x": 72,
  "size_y": 72,
  "size_z": 46,
  "snr": 3.1041601743076046,
  "spacing_tr": 3.0,
  "spacing_x": 3.0,
  "spacing_y": 3.0,
  "spacing_z": 3.0,
  "summary_bg_k": 13.892950164032591,
  "summary_bg_mad": 47.91799376595134,
  "summary_bg_mean": 208.15496088169672,
  "summary_bg_median": 32.610836029052734,
  "summary_bg_n": 189283.0,
  "summary_bg_p05": 0.05911330133676529,
  "summary_bg_p95": 1152.305419921875,
  "summary_bg_stdv": 429.71130017815847,
  "summary_fg_k": 0.2561643411426471,
  "summary_fg_mad": 923.1500897626497,
  "summary_fg_mean": 3159.506935116526,
  "summary_fg_median": 3040.2216796875,
  "summary_fg_n": 49181.0,
  "summary_fg_p05": 1731.72900390625,
  "summary_fg_p95": 4989.95556640625,
  "summary_fg_stdv": 979.3923638977539,
  "tsnr": 53.1993621555157
}