{
  "aor": 0.0023975,
  "aqi": 0.0116015747,
  "bids_meta": {
    "EchoTime": 0.04592,
    "RepetitionTime": 3,
    "SliceEncodingDirection": "k",
    "SliceTiming": [
      0,
      1.54,
      0.07,
      1.61,
      0.14,
      1.68,
      0.21,
      1.75,
      0.28,
      1.82,
      0.35,
      1.89,
      0.42,
      1.96,
      0.49,
      2.03,
      0.56,
      2.1,
      0.63,
      2.17,
      0.7,
      2.24,
      0.77,
      2.31,
      0.84,
      2.38,
      0.91,
      2.45,
      0.98,
      2.52,
      1.05,
      2.5925,
      1.12,
      2.6625,
      1.19,
      2.7325,
      1.26,
      2.8025,
      1.33,
      2.8725,
      1.4,
      2.9425,
      1.47
    ],
    "TaskName": "rest",
    "dataset": "ds003592",
    "modality": "bold",
    "session_id": "1",
    "subject_id": "254",
    "task_id": "rest"
  },
  "dummy_trs": 0,
  "dvars_nstd": 40.92487847030152,
  "dvars_std": 1.0922984501005026,
  "dvars_vstd": 0.9596517928643218,
  "efc": 0.4714582485260254,
  "fber": 979.022216796875,
  "fd_mean": 0.15981118844822434,
  "fd_num": 44,
  "fd_perc": 22.0,
  "fwhm_avg": 2.2390098822984608,
  "fwhm_x": 2.0996029629629627,
  "fwhm_y": 2.251048888888889,
  "fwhm_z": 2.3663777950435296,
  "gcor": 0.0326642,
  "gsr_x": 0.0037635175976902246,
  "gsr_y": 0.02761545591056347,
  "provenance": {
    "md5sum": "3fb747a798231136a3e2f7a07b6cdf33",
    "settings": {
      "fd_thres": 0.2,
      "testing": false
    },
    "software": "mriqc",
    "version": "23.1.0"
  },
  "size_t": 200,
  "size_x": 64,
  "size_y": 64,
  "size_z": 43,
  "snr": 2.510695377458872,
  "spacing_tr": 3.0,
  "spacing_x": 3.375,
  "spacing_y": 3.375,
  "spacing_z": 2.9999985694885254,
  "summary_bg_k": 39.05990261842275,
  "summary_bg_mad": 6.64205796718349,
  "summary_bg_mean": 23.226785012823058,
  "summary_bg_median": 11.949999809265137,
  "summary_bg_n": 142274.0,
  "summary_bg_p05": 6.119999885559082,
  "summary_bg_p95": 85.00499725341797,
  "summary_bg_stdv": 36.019052777106516,
  "summary_fg_k": 2.754324861553684,
  "summary_fg_mad": 122.97071912495502,
  "summary_fg_mean": 402.3822680242501,
  "summary_fg_median": 373.9075012207031,
  "summary_fg_n": 33854.0,
  "summary_fg_p05": 213.1599884033203,
  "summary_fg_p95": 678.3299560546875,
  "summary_fg_stdv": 148.9236735700677,
  "tsnr": 30.934780644020066
}