{
  "aor": 0.0023285221674876843,
  "aqi": 0.0042542605911330056,
  "bids_meta": {
    "EchoTime": 0.03,
    "RepetitionTime": 3.0,
    "SliceEncodingDirection": "k",
    "SliceTiming": [
      0.0,
      1.5,
      0.065,
      1.565,
      0.13,
      1.63,
      0.196,
      1.696,
      0.261,
      1.761,
      0.326,
      1.826,
      0.391,
      1.891,
      0.457,
      1.957,
      0.522,
      2.022,
      0.587,
      2.087,
      0.652,
      2.152,
      0.717,
      2.217,
      0.783,
      2.283,
      0.848,
      2.348,
      0.913,
      2.413,
      0.978,
      2.478,
      1.043,
      2.543,
      1.109,
      2.609,
      1.174,
      2.674,
      1.239,
      2.739,
      1.304,
      2.804,
      1.37,
      2.87,
      1.435,
      2.935
    ],
    "TaskName": "rest",
    "dataset": "ds003592",
    "modality": "bold",
    "session_id": "1",
    "subject_id": "161",
    "task_id": "rest"
  },
  "dummy_trs": 1,
  "dvars_nstd": 16.473835624306936,
  "dvars_std": 1.065271033613861,
  "dvars_vstd": 0.9531735056930695,
  "efc": 0.46648975360957273,
  "fber": 14111.072265625,
  "fd_mean": 0.03697057993857779,
  "fd_num": 1,
  "fd_perc": 0.49261083743842365,
  "fwhm_avg": 2.8679900000000003,
  "fwhm_x": 2.7416933333333335,
  "fwhm_y": 2.87297,
  "fwhm_z": 2.9893066666666663,
  "gcor": 0.0162724,
  "gsr_x": -0.013279913924634457,
  "gsr_y": 0.0391802079975605,
  "provenance": {
    "md5sum": "13e38f8fd00c9ae85a3c00c7c3b64b50",
    "settings": {
      "fd_thres": 0.2,
      "testing": false
    },
    "software": "mriqc",
    "version": "23.1.0"
  },
  "size_t": 203,
  "size_x": 72,
  "size_y": 72,
  "size_z": 46,
  "snr": 3.123929144831835,
  "spacing_tr": 3.0,
  "spacing_x": 3.0,
  "spacing_y": 3.0,
  "spacing_z": 3.0,
  "summary_bg_k": 22.206334801122225,
  "summary_bg_mad": 39.98643793423463,
  "summary_bg_mean": 168.25130827398286,
  "summary_bg_median": 28.517240524291992,
  "summary_bg_n": 188670.0,
  "summary_bg_p05": 0.6896551847457886,
  "summary_bg_p95": 879.5369262695312,
  "summary_bg_stdv": 350.2502025440761,
  "summary_fg_k": 1.3179622754115519,
  "summary_fg_mad": 941.7627923942136,
  "summary_fg_mean": 3563.0902166748474,
  "summary_fg_median": 3387.56396484375,
  "summary_fg_n": 49794.0,
  "summary_fg_p05": 2048.443359375,
  "summary_fg_p95": 5566.16259765625,
  "summary_fg_stdv": 1084.3811725027585,
  "tsnr": 59.22506323014386
}